excelkit_2025/__init__.py
excelkit_2025/core.py
excelkit_2025/show.py
excelkit_2025-0.1.0.dist-info/licenses/LICENSE.md
excelkit_2025-0.1.0.dist-info/METADATA
excelkit_2025-0.1.0.dist-info/WHEEL
excelkit_2025-0.1.0.dist-info/top_level.txt
excelkit_2025-0.1.0.dist-info/RECORD
