Metadata-Version: 2.4
Name: excelkit_2025
Version: 0.1.0
Summary: Excel file helper for creating, updating, and querying data using pandas.
Author-email: Avinash S <avinash.s6055@gmail.com>
License: MIT
Keywords: excel,pandas,dataframe,utility
Requires-Python: >=3.7
License-File: LICENSE.md
Requires-Dist: pandas>=1.3
Requires-Dist: openpyxl>=3.0
Dynamic: license-file
